LICENSE
MANIFEST.in
README.md
README.rst
setup.py
lrzip/__init__.py
lrzip/build_lrzip.py
lrzip.egg-info/PKG-INFO
lrzip.egg-info/SOURCES.txt
lrzip.egg-info/dependency_links.txt
lrzip.egg-info/requires.txt
lrzip.egg-info/top_level.txt