Metadata-Version: 1.1
Name: lrzip
Version: 1.0.0
Summary: Python bindings for LRZIP
Home-page: https://github.com/kata198/lrzip
Author: Tim Savannah
Author-email: kata198@gmail.com
License: LGPLv3
Keywords: lrzip,python,bindings,compression,compress,decompress,lzma,gz,bzip2,rzip,zpaq
Platform: UNKNOWN
Classifier: Development Status :: 4 - Beta
Classifier: Programming Language :: Python
Classifier: License :: OSI Approved :: GNU Lesser General Public License v3 (LGPLv3)
Classifier: Programming Language :: Python :: 2
Classifier: Programming Language :: Python :: 2
Classifier: Programming Language :: Python :: 2.7
Classifier: Programming Language :: Python :: 3
Classifier: Programming Language :: Python :: 3.3
Classifier: Programming Language :: Python :: 3.4
Classifier: Programming Language :: Python :: 3.5
Classifier: Programming Language :: Python :: 3.6
Classifier: Topic :: Software Development :: Libraries :: Python Modules
Requires: cffi
